filehydra/__init__.py
filehydra/filehydra_core.py
filehydra/filehydra_example.py
filehydra/filehydra_example2.py
filehydra/filehydra_example3.py
filehydra/filehydra_example4.py
filehydra/filehydra_example5.py
filehydra/filehydra_example6.py
filehydra/filehydra_fashiondation_model.py
filehydra/testtest.py
filehydra-0.1.5.dist-info/LICENSE
filehydra-0.1.5.dist-info/METADATA
filehydra-0.1.5.dist-info/WHEEL
filehydra-0.1.5.dist-info/top_level.txt
filehydra-0.1.5.dist-info/RECORD
