Metadata-Version: 2.1
Name: filehydra
Version: 0.1.5
Summary: A Python package focusing on file management and routine file operations
Home-page: https://github.com/DovaX/filehydra
Author: DovaX
Author-email: dovax.ai@gmail.com
License: UNKNOWN
Platform: UNKNOWN
Classifier: Programming Language :: Python :: 3
Classifier: License :: OSI Approved :: MIT License
Classifier: Operating System :: OS Independent
Requires-Python: >=3.6
Requires-Dist: pandas
